maze/__init__.py
maze/maze
maze/maze.py
maze/renderers/__init__.py
maze/renderers/pdf.py
maze/renderers/svg.py
maze/renderers/text.py
maze-3.0.0.data/scripts/maze
maze-3.0.0.dist-info/LICENSE
maze-3.0.0.dist-info/METADATA
maze-3.0.0.dist-info/WHEEL
maze-3.0.0.dist-info/top_level.txt
maze-3.0.0.dist-info/RECORD
