Metadata-Version: 2.1
Name: maze
Version: 3.0.0
Summary: Application that generates mazes
Home-page: https://github.com/daleobrien/maze
Author: Dale O'Brien
Author-email: dale@do.id.au
License: UNKNOWN
Platform: UNKNOWN
Classifier: Development Status :: 5 - Production/Stable
Classifier: Natural Language :: English
Classifier: Programming Language :: Python
Classifier: Programming Language :: Python :: 3
Requires-Python: >=3.7
License-File: LICENSE
